seed_isort_config.py
seed_isort_config-2.2.0.dist-info/LICENSE
seed_isort_config-2.2.0.dist-info/METADATA
seed_isort_config-2.2.0.dist-info/WHEEL
seed_isort_config-2.2.0.dist-info/entry_points.txt
seed_isort_config-2.2.0.dist-info/top_level.txt
seed_isort_config-2.2.0.dist-info/RECORD
